rust_native_keyring-0.2.0.dist-info/METADATA
rust_native_keyring-0.2.0.dist-info/WHEEL
rust_native_keyring-0.2.0.dist-info/licenses/LICENSE-APACHE
rust_native_keyring-0.2.0.dist-info/licenses/LICENSE-MIT
rust_native_keyring/__init__.py
rust_native_keyring/rust_native_keyring.cpython-312-arm-linux-gnueabihf.so
rust_native_keyring-0.2.0.dist-info/RECORD
