Metadata-Version: 2.4
Name: rust_native_keyring
Version: 0.2.0
Classifier: Programming Language :: Rust
Classifier: Programming Language :: Python :: Implementation :: CPython
Classifier: Programming Language :: Python :: Implementation :: PyPy
License-File: LICENSE-APACHE
License-File: LICENSE-MIT
Summary: The rust keyring crate packaged as a Python module
Keywords: rust,keyring,credential-store
Home-Page: https://github.com/open-source-cooperative/keyring-rs/wiki/Keyring
Author: Daniel Brotsky <dev@brotsky.com>
Author-email: Daniel Brotsky <dev@brotsky.com>
License: MIT OR Apache-2.0
Requires-Python: >=3.8
Project-URL: Homepage, https://github.com/open-source-cooperative/keyring-rs/wiki/Keyring
Project-URL: Source Code, https://github.com/open-source-cooperative/keyring-rs/tree/main/python/
